{
    "mcpServers": {
        "serena": {
            "command": "uvx",
            "args": [
                "--from",
                "git+https://github.com/oraios/serena",
                "serena",
                "start-mcp-server",
                "--context",
                "ide-assistant",
                "--project",
                "."
            ],
            "cwd": "."
        },
        "awslabs.cloudwatch-mcp-server": {
            "autoApprove": [],
            "disabled": false,
            "command": "uvx",
            "args": [
                "awslabs.cloudwatch-mcp-server@latest"
            ],
            "env": {
                "AWS_PROFILE": "[The AWS Profile Name to use for AWS access]",
                "FASTMCP_LOG_LEVEL": "ERROR"
            },
            "transportType": "stdio"
        },
        "context7": {
            "command": "npx",
            "args": [
                "-y",
                "@upstash/context7-mcp@latest"
            ]
        },
        "filesystem": {
            "command": "npx",
            "args": [
                "-y",
                "@modelcontextprotocol/server-filesystem",
                "/Users/username/Desktop",
                "/path/to/other/allowed/dir"
            ]
        },
        "sequentialthinking": {
            "command": "docker",
            "args": [
                "run",
                "--rm",
                "-i",
                "mcp/sequentialthinking"
            ]
        }
    }
}
